pvn_fmc_mcp/__init__.py
pvn_fmc_mcp/server.py
pvn_fmc_mcp-0.3.1.dist-info/METADATA
pvn_fmc_mcp-0.3.1.dist-info/WHEEL
pvn_fmc_mcp-0.3.1.dist-info/entry_points.txt
pvn_fmc_mcp-0.3.1.dist-info/top_level.txt
pvn_fmc_mcp-0.3.1.dist-info/RECORD
