Metadata-Version: 2.4
Name: pvn-fmc-mcp
Version: 0.3.1
Summary: An MCP server exposing FMC text output via stdio
Author: PVN
Requires-Python: >=3.9
Requires-Dist: mcp
